LICENSE
MANIFEST.in
README.rst
requirements.txt
setup.cfg
setup.py
deploy/interfaces.bu
deploy/modis_monitor.conf
deploy/modislock_init.sql
modislock_monitor/__init__.py
modislock_monitor/celery_worker.py
modislock_monitor/extensions.py
modislock_monitor/reset.py
modislock_monitor/run_monitor.py
modislock_monitor/tasks.py
modislock_monitor.egg-info/PKG-INFO
modislock_monitor.egg-info/SOURCES.txt
modislock_monitor.egg-info/dependency_links.txt
modislock_monitor.egg-info/entry_points.txt
modislock_monitor.egg-info/not-zip-safe
modislock_monitor.egg-info/requires.txt
modislock_monitor.egg-info/top_level.txt
modislock_monitor/config/__init__.py
modislock_monitor/config/default.py
modislock_monitor/config/development.py
modislock_monitor/config/production.py
modislock_monitor/database/__init__.py
modislock_monitor/database/app_api.py
modislock_monitor/database/app_api_access.py
modislock_monitor/database/controller.py
modislock_monitor/database/controller_status.py
modislock_monitor/database/database.py
modislock_monitor/database/door.py
modislock_monitor/database/door_status.py
modislock_monitor/database/events.py
modislock_monitor/database/host.py
modislock_monitor/database/host_sensors.py
modislock_monitor/database/host_status.py
modislock_monitor/database/otp_cloud_service.py
modislock_monitor/database/otp_key.py
modislock_monitor/database/pin_key.py
modislock_monitor/database/reader.py
modislock_monitor/database/reader_status.py
modislock_monitor/database/recent_24h_approved_count.py
modislock_monitor/database/recent_24h_denied_count.py
modislock_monitor/database/recent_24h_events.py
modislock_monitor/database/relay.py
modislock_monitor/database/rfid_key.py
modislock_monitor/database/rules.py
modislock_monitor/database/settings.py
modislock_monitor/database/settings_values.py
modislock_monitor/database/totp_key.py
modislock_monitor/database/u2f_key.py
modislock_monitor/database/user.py
modislock_monitor/devices/__init__.py
modislock_monitor/devices/base_device.py
modislock_monitor/devices/controller_device.py
modislock_monitor/devices/door_device.py
modislock_monitor/devices/reader_device.py
modislock_monitor/devices/reader_session/__init__.py
modislock_monitor/devices/reader_session/reader_exceptions.py
