Metadata-Version: 1.2
Name: modislock-monitor
Version: 0.1.13
Summary: Monitors slave status, door sensors, and provides validation to slave requests
Home-page: https://github.com/Modis-GmbH/ModisLock-Monitor
Author: Richard Lowe
Author-email: richard@modis.io
License: GPL
Keywords: modis,raspberry pi,lock,serial monitor
Platform: Linux
Platform: Raspberry Pi
Classifier: Development Status :: 4 - Beta
Classifier: Programming Language :: Python
Classifier: Programming Language :: Python :: 3
Classifier: Programming Language :: Python :: 3.5
Classifier: Environment :: Console
Classifier: Intended Audience :: Developers
Classifier: License :: OSI Approved
Classifier: License :: OSI Approved :: GNU Lesser General Public License v3 (LGPLv3)
Classifier: Operating System :: POSIX :: Linux
Classifier: Topic :: Security
Requires-Python: >=3.5
